{"timezone":"Europe/Tallinn","countries":{"Estonia":[{"city":"Tallinn","state":"Harjumaa","population":394024,"lat":59.43696,"lng":24.75353},{"city":"Tartu","state":"Tartu","population":91407,"lat":58.38062,"lng":26.72509},{"city":"Narva","state":"Ida-Virumaa","population":54409,"lat":59.37722,"lng":28.19028},{"city":"Pärnu","state":"Pärnumaa","population":40228,"lat":58.38588,"lng":24.49711},{"city":"Nõmme","state":"Harjumaa","population":39422,"lat":59.37757,"lng":24.68587},{"city":"Kohtla-Järve","state":"Ida-Virumaa","population":35395,"lat":59.39861,"lng":27.27306},{"city":"Viljandi","state":"Viljandimaa","population":17407,"lat":58.36319,"lng":25.59159},{"city":"Maardu","state":"Harjumaa","population":16630,"lat":59.46529,"lng":24.98215},{"city":"Rakvere","state":"Lääne-Virumaa","population":14984,"lat":59.34808,"lng":26.35784},{"city":"Kuressaare","state":"Saare","population":12698,"lat":58.25382,"lng":22.49217},{"city":"Sillamäe","state":"Ida-Virumaa","population":12480,"lat":59.39697,"lng":27.76331},{"city":"Võru","state":"Võrumaa","population":12367,"lat":57.83389,"lng":27.01944},{"city":"Tori","state":"Pärnumaa","population":11879,"lat":58.47889,"lng":24.82417},{"city":"Haapsalu","state":"Lääne","population":11805,"lat":58.93937,"lng":23.54127},{"city":"Valga","state":"Valgamaa","population":11792,"lat":57.77781,"lng":26.0473},{"city":"Jõhvi","state":"Ida-Virumaa","population":10130,"lat":59.35917,"lng":27.42111},{"city":"Keila","state":"Harjumaa","population":10068,"lat":59.30361,"lng":24.41306},{"city":"Paide","state":"Järvamaa","population":7793,"lat":58.88768,"lng":25.54042},{"city":"Kuusalu","state":"Harjumaa","population":6464,"lat":59.44389,"lng":25.44139},{"city":"Jõgeva","state":"Jõgevamaa","population":6396,"lat":58.74667,"lng":26.39389},{"city":"Männiku","state":"Harjumaa","population":5870,"lat":59.37528,"lng":24.71806},{"city":"Saue","state":"Harjumaa","population":5810,"lat":59.32258,"lng":24.54967},{"city":"Elva","state":"Tartu","population":5616,"lat":58.2225,"lng":26.42111},{"city":"Tapa","state":"Lääne-Virumaa","population":5168,"lat":59.26056,"lng":25.95861},{"city":"Laagri","state":"Harjumaa","population":5165,"lat":59.35083,"lng":24.61418},{"city":"Raasiku","state":"Harjumaa","population":5161,"lat":59.36639,"lng":25.18306},{"city":"Rapla","state":"Raplamaa","population":5132,"lat":59.00759,"lng":24.79386},{"city":"Põlva","state":"Põlvamaa","population":5115,"lat":58.06028,"lng":27.06944},{"city":"Türi","state":"Järvamaa","population":5064,"lat":58.80861,"lng":25.4325},{"city":"Toila","state":"Ida-Virumaa","population":4735,"lat":59.42127,"lng":27.50807},{"city":"Kiviõli","state":"Ida-Virumaa","population":4725,"lat":59.35306,"lng":26.97111},{"city":"Saku","state":"Harjumaa","population":4548,"lat":59.30354,"lng":24.66382},{"city":"Kunda","state":"Lääne-Virumaa","population":3996,"lat":59.48333,"lng":26.53333},{"city":"Põltsamaa","state":"Jõgevamaa","population":3933,"lat":58.6525,"lng":25.97056},{"city":"Sindi","state":"Pärnumaa","population":3906,"lat":58.40056,"lng":24.6675},{"city":"Paldiski","state":"Harjumaa","population":3542,"lat":59.35667,"lng":24.05306},{"city":"Tabasalu","state":"Harjumaa","population":3527,"lat":59.42607,"lng":24.5533},{"city":"Rummu","state":"Harjumaa","population":3488,"lat":59.53528,"lng":24.79972},{"city":"Loksa","state":"Harjumaa","population":3463,"lat":59.57639,"lng":25.72139},{"city":"Kohila","state":"Raplamaa","population":3355,"lat":59.16806,"lng":24.7575},{"city":"Ridala","state":"Lääne","population":3245,"lat":58.87667,"lng":23.61528},{"city":"Kärdla","state":"Hiiumaa","population":3160,"lat":58.99778,"lng":22.74917},{"city":"Märjamaa","state":"Raplamaa","population":3063,"lat":58.90389,"lng":24.43056},{"city":"Kunda","state":"Lääne-Virumaa","population":2865,"lat":59.49861,"lng":26.52611},{"city":"Kehra","state":"Harjumaa","population":2694,"lat":59.33611,"lng":25.32111},{"city":"Tõrva","state":"Valgamaa","population":2690,"lat":58.00278,"lng":25.935},{"city":"Narva-Jõesuu","state":"Ida-Virumaa","population":2681,"lat":59.45889,"lng":28.04083},{"city":"Jüri","state":"Harjumaa","population":2581,"lat":59.35974,"lng":24.92099},{"city":"Vändra","state":"Pärnumaa","population":2544,"lat":58.64806,"lng":25.03611},{"city":"Kadrina","state":"Lääne-Virumaa","population":2406,"lat":59.33472,"lng":26.145},{"city":"Kose","state":"Harjumaa","population":2232,"lat":59.46001,"lng":24.87824},{"city":"Otepää","state":"Valgamaa","population":2167,"lat":58.05833,"lng":26.49667},{"city":"Väike-Maarja","state":"Lääne-Virumaa","population":2155,"lat":59.12639,"lng":26.25},{"city":"Tamsalu","state":"Lääne-Virumaa","population":2119,"lat":59.15861,"lng":26.11528},{"city":"Aruküla","state":"Harjumaa","population":2113,"lat":59.36686,"lng":25.07618},{"city":"Loo","state":"Harjumaa","population":2093,"lat":59.43123,"lng":24.94949},{"city":"Haabneeme","state":"Harjumaa","population":2077,"lat":59.51358,"lng":24.82225},{"city":"Räpina","state":"Põlvamaa","population":2066,"lat":58.09806,"lng":27.46361},{"city":"Paikuse","state":"Pärnumaa","population":1996,"lat":58.37917,"lng":24.63444},{"city":"Viimsi","state":"Harjumaa","population":1740,"lat":59.50502,"lng":24.84807},{"city":"Kilingi-Nõmme","state":"Pärnumaa","population":1671,"lat":58.15028,"lng":24.96417},{"city":"Mustvee","state":"Jõgevamaa","population":1662,"lat":58.84861,"lng":26.93972},{"city":"Kiili","state":"Harjumaa","population":1584,"lat":59.30775,"lng":24.83776},{"city":"Kehtna","state":"Raplamaa","population":1579,"lat":58.93028,"lng":24.87806},{"city":"Karksi-Nuia","state":"Viljandimaa","population":1554,"lat":58.10333,"lng":25.56278},{"city":"Viimsi","state":"Harjumaa","population":1500,"lat":59.50086,"lng":24.86254},{"city":"Nõo","state":"Tartu","population":1476,"lat":58.27556,"lng":26.5375},{"city":"Järvakandi","state":"Raplamaa","population":1471,"lat":58.77889,"lng":24.82583},{"city":"Vana-Antsla","state":"Võrumaa","population":1468,"lat":57.86611,"lng":26.53222},{"city":"Lihula","state":"Pärnumaa","population":1457,"lat":58.68139,"lng":23.84528},{"city":"Aseri","state":"Lääne-Virumaa","population":1439,"lat":59.45256,"lng":26.87163},{"city":"Audru","state":"Pärnumaa","population":1430,"lat":58.40861,"lng":24.37389},{"city":"Iisaku","state":"Ida-Virumaa","population":1425,"lat":59.10139,"lng":27.30806},{"city":"Sõmeru","state":"Lääne-Virumaa","population":1350,"lat":59.36111,"lng":26.4375},{"city":"Pärnu-Jaagupi","state":"Pärnumaa","population":1341,"lat":58.61052,"lng":24.50689},{"city":"Viiratsi","state":"Viljandimaa","population":1332,"lat":58.36,"lng":25.63722},{"city":"Võhma","state":"Viljandimaa","population":1280,"lat":58.62833,"lng":25.54833},{"city":"Haljala","state":"Lääne-Virumaa","population":1233,"lat":59.43361,"lng":26.26139},{"city":"Koeru","state":"Järvamaa","population":1178,"lat":58.96306,"lng":26.03083},{"city":"Suure-Jaani","state":"Viljandimaa","population":1173,"lat":58.53611,"lng":25.47056},{"city":"Turba","state":"Harjumaa","population":1096,"lat":59.08306,"lng":24.225},{"city":"Kohtla-Nõmme","state":"Ida-Virumaa","population":1075,"lat":59.35167,"lng":27.175},{"city":"Puhja","state":"Tartu","population":1072,"lat":58.34194,"lng":26.31472},{"city":"Uuemõisa","state":"Lääne","population":1068,"lat":58.93944,"lng":23.58944},{"city":"Orissaare","state":"Saare","population":1065,"lat":58.55917,"lng":23.08262},{"city":"Sauga","state":"Pärnumaa","population":1062,"lat":58.4272,"lng":24.49496},{"city":"Riisipere","state":"Harjumaa","population":1058,"lat":59.11417,"lng":24.31056},{"city":"Abja-Paluoja","state":"Viljandimaa","population":1057,"lat":58.12528,"lng":25.34972},{"city":"Järva-Jaani","state":"Järvamaa","population":1051,"lat":59.03861,"lng":25.88639},{"city":"Ülenurme","state":"Tartu","population":1047,"lat":58.3162,"lng":26.72517},{"city":"Särevere","state":"Järvamaa","population":1035,"lat":58.79,"lng":25.42806},{"city":"Vinni","state":"Lääne-Virumaa","population":1032,"lat":59.29583,"lng":26.43222},{"city":"Vaida","state":"Harjumaa","population":1016,"lat":59.28546,"lng":24.97897},{"city":"Rakke","state":"Lääne-Virumaa","population":1015,"lat":58.98167,"lng":26.25444},{"city":"Taebla","state":"Lääne","population":990,"lat":58.95389,"lng":23.75222},{"city":"Kärla","state":"Saare","population":988,"lat":58.33583,"lng":22.25972},{"city":"Klooga","state":"Harjumaa","population":983,"lat":59.31972,"lng":24.21139},{"city":"Kose-Uuemõisa","state":"Harjumaa","population":980,"lat":59.2,"lng":25.10528},{"city":"Palivere","state":"Lääne","population":968,"lat":58.97028,"lng":23.90333},{"city":"Aravete","state":"Järvamaa","population":955,"lat":59.14167,"lng":25.76139},{"city":"Tootsi","state":"Pärnumaa","population":951,"lat":58.57806,"lng":24.7925},{"city":"Lagedi","state":"Harjumaa","population":939,"lat":59.40417,"lng":24.93892},{"city":"Mustla","state":"Pärnumaa","population":928,"lat":58.13417,"lng":25.10028},{"city":"Alu","state":"Raplamaa","population":920,"lat":59.0225,"lng":24.76083},{"city":"Püssi","state":"Ida-Virumaa","population":917,"lat":59.36,"lng":27.04972},{"city":"Aegviidu","state":"Harjumaa","population":910,"lat":59.28583,"lng":25.61417},{"city":"Tihemetsa","state":"Pärnumaa","population":894,"lat":58.14528,"lng":25.04417},{"city":"Vasalemma","state":"Harjumaa","population":856,"lat":59.24417,"lng":24.29},{"city":"Käina","state":"Hiiumaa","population":854,"lat":58.82848,"lng":22.77711},{"city":"Häädemeeste","state":"Pärnumaa","population":851,"lat":58.08114,"lng":24.49719},{"city":"Kareda","state":"Järvamaa","population":846,"lat":58.96083,"lng":25.81},{"city":"Kiiu","state":"Harjumaa","population":833,"lat":59.44778,"lng":25.37944},{"city":"Peetri","state":"Harjumaa","population":824,"lat":59.39468,"lng":24.81452},{"city":"Voka","state":"Ida-Virumaa","population":823,"lat":59.40776,"lng":27.58263},{"city":"Mustla","state":"Viljandimaa","population":818,"lat":58.23333,"lng":25.86667},{"city":"Väimela","state":"Võrumaa","population":799,"lat":57.89083,"lng":27.01889},{"city":"Siimusti","state":"Jõgevamaa","population":797,"lat":58.72972,"lng":26.33944},{"city":"Kostivere","state":"Harjumaa","population":790,"lat":59.42734,"lng":25.09719},{"city":"Lehtmetsa","state":"Harjumaa","population":789,"lat":59.32,"lng":25.35694},{"city":"Harku","state":"Harjumaa","population":781,"lat":59.1325,"lng":24.37111},{"city":"Avinurme","state":"Jõgevamaa","population":779,"lat":58.98222,"lng":26.86417},{"city":"Lohkva","state":"Tartu","population":776,"lat":58.36917,"lng":26.79806},{"city":"Vastseliina","state":"Võrumaa","population":773,"lat":57.72972,"lng":27.29361},{"city":"Pajusti","state":"Lääne-Virumaa","population":756,"lat":59.27444,"lng":26.42333},{"city":"Puka","state":"Valgamaa","population":748,"lat":58.04972,"lng":26.22639},{"city":"Mõisaküla","state":"Viljandimaa","population":745,"lat":58.09222,"lng":25.18639},{"city":"Rõngu","state":"Tartu","population":738,"lat":58.14528,"lng":26.24806},{"city":"Parksepa","state":"Võrumaa","population":737,"lat":57.90972,"lng":26.98306},{"city":"Ramsi","state":"Viljandimaa","population":732,"lat":58.30583,"lng":25.53528},{"city":"Püünsi","state":"Harjumaa","population":729,"lat":59.54696,"lng":24.80206},{"city":"Suure-Kambja","state":"Tartu","population":722,"lat":58.22056,"lng":26.70611},{"city":"Kallaste","state":"Tartu","population":714,"lat":58.66312,"lng":27.16164},{"city":"Järve","state":"Ida-Virumaa","population":682,"lat":59.40583,"lng":27.31111},{"city":"Väätsa","state":"Järvamaa","population":679,"lat":58.88556,"lng":25.44639},{"city":"Valkla","state":"Harjumaa","population":663,"lat":59.47297,"lng":25.32321},{"city":"Olustvere","state":"Viljandimaa","population":647,"lat":58.55361,"lng":25.56278},{"city":"Puurmani","state":"Jõgevamaa","population":646,"lat":58.57833,"lng":26.27528},{"city":"Adavere","state":"Jõgevamaa","population":646,"lat":58.70611,"lng":25.89917},{"city":"Tõstamaa","state":"Pärnumaa","population":639,"lat":58.3325,"lng":23.99972},{"city":"Kanepi","state":"Põlvamaa","population":638,"lat":57.98306,"lng":26.75639},{"city":"Ääsmäe","state":"Harjumaa","population":638,"lat":59.23995,"lng":24.51599},{"city":"Võnnu","state":"Tartu","population":630,"lat":58.27833,"lng":27.04806},{"city":"Mammaste","state":"Põlvamaa","population":616,"lat":58.06667,"lng":27.04528},{"city":"Ahja","state":"Põlvamaa","population":616,"lat":58.20389,"lng":27.07333},{"city":"Pringi","state":"Harjumaa","population":603,"lat":59.53459,"lng":24.79726},{"city":"Risti","state":"Pärnumaa","population":597,"lat":58.56056,"lng":23.83944},{"city":"Roela","state":"Lääne-Virumaa","population":596,"lat":59.17028,"lng":26.60028},{"city":"Sonda","state":"Ida-Virumaa","population":594,"lat":59.34361,"lng":26.83639},{"city":"Kuremaa","state":"Jõgevamaa","population":594,"lat":58.73667,"lng":26.5225},{"city":"Luunja","state":"Tartu","population":579,"lat":58.35583,"lng":26.88083},{"city":"Salme","state":"Saare","population":576,"lat":58.16139,"lng":22.26222},{"city":"Käärdi","state":"Tartu","population":573,"lat":58.20806,"lng":26.41139},{"city":"Vana-Vigala","state":"Raplamaa","population":572,"lat":58.76972,"lng":24.27361},{"city":"Kõrveküla","state":"Tartu","population":571,"lat":58.42417,"lng":26.78222},{"city":"Juuru","state":"Raplamaa","population":571,"lat":59.06472,"lng":24.95028},{"city":"Hulja","state":"Lääne-Virumaa","population":569,"lat":59.35222,"lng":26.21417},{"city":"Luige","state":"Harjumaa","population":562,"lat":59.32723,"lng":24.77613},{"city":"Ardu","state":"Harjumaa","population":559,"lat":59.10056,"lng":25.37083},{"city":"Kiisa","state":"Harjumaa","population":551,"lat":59.23694,"lng":24.68889},{"city":"Veriora","state":"Põlvamaa","population":549,"lat":58.00417,"lng":27.35194},{"city":"Kose","state":"Võrumaa","population":549,"lat":57.81278,"lng":27.03694},{"city":"Lavassaare","state":"Pärnumaa","population":548,"lat":58.51139,"lng":24.38889},{"city":"Koosa","state":"Tartu","population":548,"lat":58.52,"lng":27.07417},{"city":"Aste","state":"Saare","population":546,"lat":58.34361,"lng":22.45889},{"city":"Himmaste","state":"Põlvamaa","population":545,"lat":58.07694,"lng":27.07417},{"city":"Kaerepere","state":"Raplamaa","population":544,"lat":58.96556,"lng":24.84361},{"city":"Mäetaguse","state":"Ida-Virumaa","population":542,"lat":59.22972,"lng":27.27222},{"city":"Palamuse","state":"Jõgevamaa","population":541,"lat":58.685,"lng":26.57889},{"city":"Orgita","state":"Raplamaa","population":540,"lat":58.92861,"lng":24.42889},{"city":"Virtsu","state":"Pärnumaa","population":539,"lat":58.57,"lng":23.52389},{"city":"Torma","state":"Jõgevamaa","population":533,"lat":58.81278,"lng":26.73833},{"city":"Lehola","state":"Harjumaa","population":530,"lat":59.2925,"lng":24.31139},{"city":"Karksi","state":"Viljandimaa","population":528,"lat":58.11722,"lng":25.58778},{"city":"Uulu","state":"Pärnumaa","population":524,"lat":58.28361,"lng":24.58722},{"city":"Võiste","state":"Pärnumaa","population":520,"lat":58.46667,"lng":24.48333},{"city":"Vana-Võidu","state":"Viljandimaa","population":517,"lat":58.39056,"lng":25.65417},{"city":"Võisiku","state":"Jõgevamaa","population":516,"lat":58.62833,"lng":25.92056},{"city":"Randvere","state":"Harjumaa","population":513,"lat":59.50823,"lng":24.90655},{"city":"Ilmatsalu","state":"Tartu","population":512,"lat":58.38639,"lng":26.54667},{"city":"Vastse-Kuuste","state":"Põlvamaa","population":510,"lat":58.16778,"lng":26.92861},{"city":"Türi-Alliku","state":"Järvamaa","population":507,"lat":58.81583,"lng":25.45389},{"city":"Olgina","state":"Ida-Virumaa","population":504,"lat":59.39528,"lng":28.12528},{"city":"Valjala","state":"Saare","population":503,"lat":58.40611,"lng":22.80111},{"city":"Rõuge","state":"Võrumaa","population":442,"lat":57.72778,"lng":26.90972},{"city":"Alatskivi","state":"Tartu","population":430,"lat":58.59806,"lng":27.13361},{"city":"Värska","state":"Võrumaa","population":414,"lat":57.95806,"lng":27.63806},{"city":"Linaküla","state":"Pärnumaa","population":119,"lat":58.13722,"lng":23.97444},{"city":"Hullo","state":"Lääne","population":104,"lat":58.99004,"lng":23.24441},{"city":"Vaiatu","state":"Lääne-Virumaa","population":102,"lat":59.35556,"lng":25.99528},{"city":"Ruhnu","state":"Saare","population":64,"lat":57.80028,"lng":23.24833},{"city":"Tehumardi","state":"Saare","population":0,"lat":58.18027,"lng":22.24646},{"city":"Liiva","state":"Saare","population":0,"lat":58.60194,"lng":23.24694},{"city":"Kurepalu","state":"Tartu","population":0,"lat":58.31861,"lng":26.84083},{"city":"Kose","state":"Harjumaa","population":0,"lat":59.17889,"lng":25.17306},{"city":"Antsla","state":"Võrumaa","population":0,"lat":57.82556,"lng":26.54056},{"city":"Harku","state":"Harjumaa","population":0,"lat":59.38641,"lng":24.57176}]}}