{"timezone":"Indian/Antananarivo","countries":{"Madagascar":[{"city":"Antananarivo","state":"Analamanga","population":1349501,"lat":-18.91368,"lng":47.53613},{"city":"Toamasina","state":"Atsinanana","population":345107,"lat":-18.1492,"lng":49.40234},{"city":"Antsirabe","state":"Vakinankaratra","population":260907,"lat":-19.86586,"lng":47.03333},{"city":"Mahajanga","state":"Boeny","population":260556,"lat":-15.71667,"lng":46.31667},{"city":"Fianarantsoa","state":"Upper Matsiatra","population":203105,"lat":-21.45267,"lng":47.08569},{"city":"Toliara","state":"Atsimo-Andrefana","population":178725,"lat":-23.35,"lng":43.66667},{"city":"Antsiranana","state":"Diana","population":136959,"lat":-12.31732,"lng":49.29188},{"city":"Sambava","state":"Sava","population":89003,"lat":-14.26667,"lng":50.16667},{"city":"Imerintsiatosika","state":"Itasy","population":74085,"lat":-18.98333,"lng":47.31667},{"city":"Antalaha","state":"Sava","population":71898,"lat":-14.90033,"lng":50.27876},{"city":"Tôlanaro","state":"Anosy","population":71258,"lat":-25.03249,"lng":46.98329},{"city":"Antanifotsy","state":"Vakinankaratra","population":70626,"lat":-19.65,"lng":47.31667},{"city":"Ambovombe","state":"Androy","population":69265,"lat":-25.17838,"lng":46.08722},{"city":"Ambilobe","state":"Diana","population":66029,"lat":-13.2,"lng":49.05},{"city":"Ambanja","state":"Diana","population":63884,"lat":-13.669,"lng":48.453},{"city":"Moramanga","state":"Alaotra Mangoro","population":60456,"lat":-18.94948,"lng":48.23007},{"city":"Antsalova","state":"Melaky","population":58280,"lat":-18.66667,"lng":44.61667},{"city":"Morondava","state":"Menabe","population":56671,"lat":-20.28869,"lng":44.31782},{"city":"Hell-Ville","state":"Diana","population":53219,"lat":-13.39718,"lng":48.26663},{"city":"Ivato","state":"Analamanga","population":52376,"lat":-18.8,"lng":47.48333},{"city":"Ambatondrazaka","state":"Alaotra Mangoro","population":50463,"lat":-17.83333,"lng":48.41667},{"city":"Amboasary","state":"Anosy","population":48705,"lat":-25.03333,"lng":46.38333},{"city":"Tsiroanomandidy","state":"Bongolava","population":47087,"lat":-18.76969,"lng":46.04653},{"city":"Manakara","state":"Fitovinany Region","population":46850,"lat":-22.14862,"lng":48.01055},{"city":"Ambalavao","state":"Upper Matsiatra","population":45784,"lat":-21.83333,"lng":46.93333},{"city":"Maroantsetra","state":"Analanjirofo","population":45041,"lat":-15.43527,"lng":49.73794},{"city":"Fenoarivo Atsinanana","state":"Analanjirofo","population":44199,"lat":-17.38095,"lng":49.40826},{"city":"Ambositra","state":"Amoron'i Mania","population":43504,"lat":-20.53034,"lng":47.24344},{"city":"Soavinandriana","state":"Itasy","population":42410,"lat":-19.16667,"lng":46.73333},{"city":"Ihosy","state":"Ihorombe","population":41892,"lat":-22.40293,"lng":46.12576},{"city":"Marovoay","state":"Boeny","population":41611,"lat":-16.11064,"lng":46.64383},{"city":"Vangaindrano","state":"Atsimo-Atsinanana","population":40813,"lat":-23.35,"lng":47.6},{"city":"Antsohihy","state":"Sofia","population":40512,"lat":-14.87959,"lng":47.98751},{"city":"Ampanihy","state":"Atsimo-Andrefana","population":40244,"lat":-24.6937,"lng":44.74581},{"city":"Mahanoro","state":"Atsinanana","population":40033,"lat":-19.9,"lng":48.8},{"city":"Ambatofinandrahana","state":"Amoron'i Mania","population":39618,"lat":-20.55284,"lng":46.80365},{"city":"Andilamena","state":"Alaotra Mangoro","population":39428,"lat":-17.01009,"lng":48.57313},{"city":"Soanierana Ivongo","state":"Analanjirofo","population":39271,"lat":-16.91667,"lng":49.58333},{"city":"Ikongo","state":"Fitovinany Region","population":38851,"lat":-21.88333,"lng":47.43333},{"city":"Vavatenina","state":"Analanjirofo","population":37861,"lat":-17.46667,"lng":49.2},{"city":"Faratsiho","state":"Vakinankaratra","population":37563,"lat":-19.4,"lng":46.95},{"city":"Mananara","state":"Analanjirofo","population":37224,"lat":-16.16864,"lng":49.76622},{"city":"Nosy Varika","state":"Vatovavy Region","population":37152,"lat":-20.58333,"lng":48.53333},{"city":"Farafangana","state":"Atsimo-Atsinanana","population":36724,"lat":-22.82223,"lng":47.82615},{"city":"Andapa","state":"Sava","population":36660,"lat":-14.65,"lng":49.65},{"city":"Betafo","state":"Vakinankaratra","population":36364,"lat":-19.83333,"lng":46.85},{"city":"Ambato Boeny","state":"Boeny","population":35432,"lat":-16.46667,"lng":46.71667},{"city":"Amparafaravola","state":"Alaotra Mangoro","population":35266,"lat":-17.5876,"lng":48.22391},{"city":"Ambatolampy","state":"Vakinankaratra","population":34198,"lat":-19.38333,"lng":47.41667},{"city":"Maromandia","state":"Sofia","population":33596,"lat":-14.21667,"lng":48.08333},{"city":"Ambodimanga II","state":"Analanjirofo","population":33000,"lat":-17.26667,"lng":49.16667},{"city":"Bealanana","state":"Sofia","population":32764,"lat":-14.54329,"lng":48.74981},{"city":"Antsohimbondrona","state":"Diana","population":32080,"lat":-13.08333,"lng":48.85},{"city":"Fandriana","state":"Amoron'i Mania","population":30958,"lat":-20.23333,"lng":47.38333},{"city":"Mampikony","state":"Sofia","population":30282,"lat":-16.092,"lng":47.647},{"city":"Arivonimamo","state":"Itasy","population":29997,"lat":-19.01667,"lng":47.18333},{"city":"Tsiombe","state":"Androy","population":29825,"lat":-25.3,"lng":45.48333},{"city":"Ankazobe","state":"Analamanga","population":28430,"lat":-18.31667,"lng":47.11667},{"city":"Ambodifotatra","state":"Analanjirofo","population":28406,"lat":-16.98333,"lng":49.85},{"city":"Sahavato","state":"Vatovavy Region","population":28000,"lat":-20.6,"lng":48.33333},{"city":"Maevatanana","state":"Betsiboka","population":27459,"lat":-16.95,"lng":46.83333},{"city":"Betioky","state":"Atsimo-Andrefana","population":27125,"lat":-23.72065,"lng":44.38069},{"city":"Vohipaho","state":"Atsimo-Atsinanana","population":27000,"lat":-23.55,"lng":47.5},{"city":"Miandrarivo","state":"Vakinankaratra","population":27000,"lat":-19.43333,"lng":46.75},{"city":"Mananjary","state":"Vatovavy Region","population":26712,"lat":-21.23034,"lng":48.34173},{"city":"Tsaratanana","state":"Betsiboka","population":26446,"lat":-16.79706,"lng":47.65165},{"city":"Marolambo","state":"Atsinanana","population":26160,"lat":-20.05,"lng":48.11667},{"city":"Ankazoabo","state":"Atsimo-Andrefana","population":25961,"lat":-22.28333,"lng":44.51667},{"city":"Anjozorobe","state":"Analamanga","population":25541,"lat":-18.4,"lng":47.86667},{"city":"Vohibinany","state":"Atsinanana","population":25311,"lat":-17.35,"lng":49.03333},{"city":"Ambohidratrimo","state":"Analamanga","population":25163,"lat":-18.818,"lng":47.43382},{"city":"Ampahana","state":"Sava","population":25000,"lat":-14.75,"lng":50.21667},{"city":"Morombe","state":"Atsimo-Andrefana","population":23961,"lat":-21.74499,"lng":43.36055},{"city":"Boriziny","state":"Sofia","population":23906,"lat":-15.55,"lng":47.66667},{"city":"Belo sur Tsiribihina","state":"Menabe","population":23900,"lat":-19.69787,"lng":44.54587},{"city":"Maintirano","state":"Melaky","population":23609,"lat":-18.06354,"lng":44.02951},{"city":"Manjakandriana","state":"Analamanga","population":23498,"lat":-18.91667,"lng":47.8},{"city":"Iharan̈a","state":"Sava","population":23349,"lat":-13.35,"lng":50.0},{"city":"Beloha","state":"Androy","population":23021,"lat":-25.16667,"lng":45.05},{"city":"Sakaraha","state":"Atsimo-Andrefana","population":21826,"lat":-22.9,"lng":44.53333},{"city":"Miandrivazo","state":"Menabe","population":21627,"lat":-19.52905,"lng":45.45559},{"city":"Soanindrariny","state":"Vakinankaratra","population":21000,"lat":-19.9,"lng":47.23333},{"city":"Sitampiky","state":"Boeny","population":21000,"lat":-16.66667,"lng":46.1},{"city":"Ampasimanolotra","state":"Atsinanana","population":21000,"lat":-18.81667,"lng":49.06667},{"city":"Bekily","state":"Androy","population":20915,"lat":-24.21667,"lng":45.31667},{"city":"Vondrozo","state":"Atsimo-Atsinanana","population":19949,"lat":-22.81667,"lng":47.28333},{"city":"Fenoarivo Be","state":"Bongolava","population":19605,"lat":-18.43333,"lng":46.56667},{"city":"Beroroha","state":"Atsimo-Andrefana","population":18632,"lat":-21.66667,"lng":45.16667},{"city":"Befandriana","state":"Sofia","population":18596,"lat":-15.2567,"lng":48.54249},{"city":"Betroka","state":"Anosy","population":18350,"lat":-23.26667,"lng":46.08333},{"city":"Sadabe","state":"Analamanga","population":17000,"lat":-18.63333,"lng":47.7},{"city":"Ambohitrolomahitsy","state":"Analamanga","population":17000,"lat":-18.7,"lng":47.68333},{"city":"Amboanjo","state":"Fitovinany Region","population":17000,"lat":-22.0,"lng":47.85},{"city":"Vatomandry","state":"Atsinanana","population":16771,"lat":-19.33018,"lng":48.97791},{"city":"Ifanadiana","state":"Vatovavy Region","population":16607,"lat":-21.3,"lng":47.63333},{"city":"Ambarakaraka","state":"Diana","population":16114,"lat":-13.5,"lng":48.86667},{"city":"Ankazondandy","state":"Analamanga","population":16000,"lat":-18.7,"lng":47.78333},{"city":"Alarobia","state":"Analamanga","population":16000,"lat":-18.96667,"lng":47.73333},{"city":"Vohipeno","state":"Fitovinany Region","population":15622,"lat":-22.35,"lng":47.83333},{"city":"Ikalamavony","state":"Upper Matsiatra","population":15601,"lat":-21.15,"lng":46.58333},{"city":"Soalala","state":"Boeny","population":15174,"lat":-16.1,"lng":45.31667},{"city":"Kopoky","state":"Androy","population":15000,"lat":-25.2,"lng":45.2},{"city":"Ifatsy","state":"Fitovinany Region","population":15000,"lat":-22.4,"lng":47.75},{"city":"Miarinarivo","state":"Itasy","population":13883,"lat":-18.95873,"lng":46.90553},{"city":"Tranovaho","state":"Androy","population":13000,"lat":-25.3,"lng":44.96667},{"city":"Antsirabe Afovoany","state":"Sofia","population":13000,"lat":-15.95,"lng":48.96667},{"city":"Ambohimahasoa","state":"Upper Matsiatra","population":12291,"lat":-21.11667,"lng":47.21667},{"city":"Besalampy","state":"Melaky","population":12000,"lat":-16.75,"lng":44.48333},{"city":"Antakotako","state":"Analanjirofo","population":11000,"lat":-15.31667,"lng":49.8},{"city":"Marovantaza","state":"Sofia","population":10504,"lat":-15.38333,"lng":47.66667},{"city":"Andovoranto","state":"Atsinanana","population":10429,"lat":-18.95443,"lng":49.1094},{"city":"Analalava","state":"Sofia","population":10349,"lat":-14.63333,"lng":47.75},{"city":"Sahatavy","state":"Analanjirofo","population":10000,"lat":-17.45,"lng":49.0},{"city":"Miadanandriana","state":"Analamanga","population":10000,"lat":-19.03333,"lng":47.78333},{"city":"Mantasoa","state":"Analamanga","population":10000,"lat":-19.01667,"lng":47.83333},{"city":"Mahabe","state":"Melaky","population":10000,"lat":-17.08333,"lng":45.33333},{"city":"Ambodivoara","state":"Sava","population":10000,"lat":-14.33333,"lng":49.98333},{"city":"Fandrandava","state":"Upper Matsiatra","population":9000,"lat":-21.51667,"lng":47.25},{"city":"Marovatolena","state":"Sofia","population":8769,"lat":-15.18333,"lng":47.65},{"city":"Merikanjaka","state":"Analamanga","population":8000,"lat":-19.13333,"lng":47.85},{"city":"Ivato","state":"Atsimo-Atsinanana","population":8000,"lat":-22.41667,"lng":47.26667},{"city":"Bemaitso","state":"Alaotra Mangoro","population":8000,"lat":-17.06667,"lng":48.5},{"city":"Ambohitrandriamanitra","state":"Analamanga","population":8000,"lat":-19.08333,"lng":47.78333},{"city":"Mahavelona","state":"Atsinanana","population":7987,"lat":-17.68475,"lng":49.50869},{"city":"Sadjoavato","state":"Diana","population":7600,"lat":-12.61667,"lng":49.35},{"city":"Sambaina","state":"Analamanga","population":7000,"lat":-18.9,"lng":47.78333},{"city":"Manato","state":"Atsimo-Atsinanana","population":7000,"lat":-22.4,"lng":47.48333},{"city":"Beteza","state":"Androy","population":7000,"lat":-24.45,"lng":45.11667},{"city":"Behompy","state":"Atsimo-Andrefana","population":7000,"lat":-23.25,"lng":43.85},{"city":"Vohimanitra","state":"Fitovinany Region","population":6000,"lat":-21.7,"lng":47.7},{"city":"Ranohira","state":"Ihorombe","population":6000,"lat":-22.48333,"lng":45.4},{"city":"Anjepy","state":"Analamanga","population":6000,"lat":-18.85,"lng":47.71667},{"city":"Ambohitseheno","state":"Analamanga","population":6000,"lat":-18.78333,"lng":47.8},{"city":"Nandihizana","state":"Analamanga","population":5000,"lat":-18.9,"lng":47.71667},{"city":"Ambatolaona","state":"Analamanga","population":5000,"lat":-18.93333,"lng":47.9},{"city":"Savana","state":"Fitovinany Region","population":4000,"lat":-22.38333,"lng":47.9},{"city":"Antanimena","state":"Atsimo-Andrefana","population":4000,"lat":-23.55,"lng":44.1},{"city":"Anandravy","state":"Upper Matsiatra","population":4000,"lat":-22.9,"lng":47.36667},{"city":"Ambalasoa","state":"Anosy","population":4000,"lat":-23.11667,"lng":46.0},{"city":"Anakao","state":"Atsimo-Andrefana","population":3000,"lat":-23.66667,"lng":43.65},{"city":"Mahalina","state":"Diana","population":2217,"lat":-12.53333,"lng":48.81667},{"city":"Manja","state":"Menabe","population":0,"lat":-21.43333,"lng":44.33333},{"city":"Mandritsara","state":"Sofia","population":0,"lat":-15.85744,"lng":48.82824},{"city":"Andramasina","state":"Analamanga","population":0,"lat":-19.18785,"lng":47.59016},{"city":"Amboasary","state":"Anosy","population":0,"lat":-24.33333,"lng":45.95},{"city":"Antsampanimahazo","state":"Vakinankaratra","population":0,"lat":-19.63988,"lng":47.1565}]}}